ak_test_ti_client/__init__.py
ak_test_ti_client/api_client.py
ak_test_ti_client/api_response.py
ak_test_ti_client/configuration.py
ak_test_ti_client/exceptions.py
ak_test_ti_client/py.typed
ak_test_ti_client/rest.py
ak_test_ti_client/api/__init__.py
ak_test_ti_client/api/pet_api.py
ak_test_ti_client/api/store_api.py
ak_test_ti_client/api/user_api.py
ak_test_ti_client/models/__init__.py
ak_test_ti_client/models/address.py
ak_test_ti_client/models/api_response.py
ak_test_ti_client/models/category.py
ak_test_ti_client/models/customer.py
ak_test_ti_client/models/order.py
ak_test_ti_client/models/pet.py
ak_test_ti_client/models/tag.py
ak_test_ti_client/models/user.py
ak_test_ti_client-1.0.0.dist-info/METADATA
ak_test_ti_client-1.0.0.dist-info/WHEEL
ak_test_ti_client-1.0.0.dist-info/top_level.txt
ak_test_ti_client-1.0.0.dist-info/RECORD
